scanimage_meta/__init__.py
scanimage_meta/scanimage_meta.py
scanimage_meta-0.1.0.dist-info/LICENSE.txt
scanimage_meta-0.1.0.dist-info/WHEEL
scanimage_meta-0.1.0.dist-info/METADATA
scanimage_meta-0.1.0.dist-info/RECORD
